simat_core/__init__.py
simat_core/base/errors.py
simat_core/base/session.py
simat_core/base/step.py
simat_core/base/suit.py
simat_core/utils/step.py
simat_core-0.1.0.dist-info/METADATA
simat_core-0.1.0.dist-info/WHEEL
simat_core-0.1.0.dist-info/top_level.txt
simat_core-0.1.0.dist-info/RECORD
