Metadata-Version: 2.1
Name: simat-core
Version: 0.1.0
Summary: simple autoflow framework
Home-page: UNKNOWN
Author: linxs
Author-email: cakelinxs@outlook.com
License: UNKNOWN
Platform: UNKNOWN
Classifier: Programming Language :: Python :: 3
Classifier: License :: OSI Approved :: MIT License
Classifier: Operating System :: OS Independent
Requires-Dist: httpx
